{
  "data": {
    "article": {},
    "attachments": {},
    "author_id": "1993150970705199108",
    "conversation_id": "2047131321752060116",
    "created_at": "2026-04-23T14:12:14.000Z",
    "edit_controls": {
      "editable_until": "2026-04-23T15:12:14.000Z",
      "edits_remaining": 5,
      "is_edit_eligible": false
    },
    "edit_history_tweet_ids": [
      "2047317627702575469"
    ],
    "entities": {
      "mentions": [
        {
          "end": 13,
          "id": "2030832351656493056",
          "start": 0,
          "username": "Suintouhea2t"
        }
      ]
    },
    "geo": {},
    "id": "2047317627702575469",
    "in_reply_to_user_id": "2030832351656493056",
    "lang": "zh",
    "note_tweet": {
      "entities": {}
    },
    "possibly_sensitive": false,
    "public_metrics": {
      "bookmark_count": 0,
      "impression_count": 0,
      "like_count": 0,
      "quote_count": 0,
      "reply_count": 0,
      "retweet_count": 0
    },
    "referenced_tweets": [
      {
        "id": "2047131321752060116",
        "type": "replied_to"
      }
    ],
    "reply_settings": "everyone",
    "text": "@Suintouhea2t 娜娜警官能不能火速出警这种啊😭🏳️🏳️"
  },
  "includes": {
    "media": [
      {
        "height": 2048,
        "media_key": "3_2047131305390018560",
        "public_metrics": {},
        "type": "photo",
        "url": "https://pbs.twimg.com/media/HGjfE3pakAA08-S.jpg",
        "width": 946
      }
    ],
    "tweets": [
      {
        "article": {},
        "attachments": {},
        "author_id": "1993150970705199108",
        "conversation_id": "2047131321752060116",
        "created_at": "2026-04-23T14:12:14.000Z",
        "edit_controls": {
          "editable_until": "2026-04-23T15:12:14.000Z",
          "edits_remaining": 5,
          "is_edit_eligible": false
        },
        "edit_history_tweet_ids": [
          "2047317627702575469"
        ],
        "entities": {
          "mentions": [
            {
              "end": 13,
              "id": "2030832351656493056",
              "start": 0,
              "username": "Suintouhea2t"
            }
          ]
        },
        "geo": {},
        "id": "2047317627702575469",
        "in_reply_to_user_id": "2030832351656493056",
        "lang": "zh",
        "note_tweet": {
          "entities": {}
        },
        "possibly_sensitive": false,
        "public_metrics": {
          "bookmark_count": 0,
          "impression_count": 0,
          "like_count": 0,
          "quote_count": 0,
          "reply_count": 0,
          "retweet_count": 0
        },
        "referenced_tweets": [
          {
            "id": "2047131321752060116",
            "type": "replied_to"
          }
        ],
        "reply_settings": "everyone",
        "text": "@Suintouhea2t 娜娜警官能不能火速出警这种啊😭🏳️🏳️"
      },
      {
        "article": {},
        "attachments": {
          "media_keys": [
            "3_2047131305390018560"
          ]
        },
        "author_id": "2030832351656493056",
        "conversation_id": "2047131321752060116",
        "created_at": "2026-04-23T01:51:55.000Z",
        "edit_controls": {
          "editable_until": "2026-04-23T02:51:55.000Z",
          "edits_remaining": 5,
          "is_edit_eligible": true
        },
        "edit_history_tweet_ids": [
          "2047131321752060116"
        ],
        "entities": {
          "urls": [
            {
              "display_url": "pic.x.com/s6byHL74VK",
              "end": 30,
              "expanded_url": "https://x.com/Suintouhea2t/status/2047131321752060116/photo/1",
              "media_key": "3_2047131305390018560",
              "start": 7,
              "url": "https://t.co/s6byHL74VK"
            }
          ]
        },
        "geo": {},
        "id": "2047131321752060116",
        "lang": "ja",
        "note_tweet": {
          "entities": {}
        },
        "possibly_sensitive": false,
        "public_metrics": {
          "bookmark_count": 2,
          "impression_count": 17567,
          "like_count": 206,
          "quote_count": 1,
          "reply_count": 46,
          "retweet_count": 1
        },
        "reply_settings": "everyone",
        "text": "抖人蠢逼死了 https://t.co/s6byHL74VK"
      }
    ],
    "users": [
      {
        "created_at": "2025-11-25T02:55:07.000Z",
        "derived": {
          "locations": [
            {
              "country_code": "JP",
              "full_name": "Shibuya-ku, Tōkyō, Japan",
              "geo": {
                "coordinates": [
                  139.69821,
                  35.66404
                ],
                "type": "Point"
              },
              "locality": "Shibuya-ku",
              "region": "Tōkyō",
              "sub_region": "Shibuya-ku"
            }
          ]
        },
        "description": "我只想疯狂自残嗑药吸毒做爱\n查成分回fo",
        "id": "1993150970705199108",
        "location": "Shibuya-ku, Tokyo",
        "name": "naiiiiiiiiiiiiiii",
        "pinned_tweet_id": "2043196929312694563",
        "profile_image_url": "https://pbs.twimg.com/profile_images/1993151610718240768/zNZFleGK_normal.jpg",
        "protected": false,
        "public_metrics": {
          "followers_count": 702,
          "following_count": 165,
          "like_count": 15259,
          "listed_count": 1,
          "media_count": 90,
          "tweet_count": 986
        },
        "username": "Nana_naiiiiiii",
        "verified": false
      },
      {
        "created_at": "2026-03-09T02:27:34.000Z",
        "description": "一个患有精神病的用户🧠🤍｜自伤🩸OD💊｜｜ISFP-T (´-ω-`)｜同类回fo🎹𝄞♡🪽提问箱https://t.co/AWOjVlhb0X 老公是将太郎李炤熙，男的别来骚扰我。赞赏的用于买小裙子",
        "entities": {
          "description": {
            "urls": [
              {
                "display_url": "ngl.link/suintouhea2t",
                "end": 71,
                "expanded_url": "http://ngl.link/suintouhea2t",
                "start": 48,
                "url": "https://t.co/AWOjVlhb0X"
              }
            ]
          }
        },
        "id": "2030832351656493056",
        "location": "墓地🪦",
        "name": "Moe",
        "pinned_tweet_id": "2043268852448928043",
        "profile_image_url": "https://pbs.twimg.com/profile_images/2042123320003588097/bsh5B1an_normal.jpg",
        "protected": false,
        "public_metrics": {
          "followers_count": 581,
          "following_count": 456,
          "like_count": 2958,
          "listed_count": 0,
          "media_count": 111,
          "tweet_count": 2185
        },
        "username": "Suintouhea2t",
        "verified": false
      }
    ]
  }
}